pyubertooth/__init__.py
pyubertooth/bluetooth_packet.py
pyubertooth/ubertooth.py
pyubertooth-0.2.data/scripts/pyubertooth_dump
pyubertooth-0.2.data/scripts/pyubertooth_rx
pyubertooth-0.2.dist-info/METADATA
pyubertooth-0.2.dist-info/RECORD
pyubertooth-0.2.dist-info/WHEEL
pyubertooth-0.2.dist-info/top_level.txt
