Metadata-Version: 2.1
Name: pyubertooth
Version: 0.2
Summary: Pure Python Library for Ubertooth
Home-page: https://github.com/haim0n/pyubertooth
Author: Ryan Holeman
Maintainer: Haim Daniel
License: UNKNOWN
Platform: UNKNOWN
Classifier: Programming Language :: Python :: 2
Classifier: License :: OSI Approved :: GNU General Public License (GPL)
Classifier: Operating System :: OS Independent
Requires-Dist: pyusb
